README.md
setup.py
msu_vqmt/__init__.py
msu_vqmt/vqmt_shared_lib.py
msu_vqmt.egg-info/PKG-INFO
msu_vqmt.egg-info/SOURCES.txt
msu_vqmt.egg-info/dependency_links.txt
msu_vqmt.egg-info/requires.txt
msu_vqmt.egg-info/top_level.txt