Metadata-Version: 2.1
Name: msu-vqmt
Version: 0.2
Summary: MSU VQMT Python Wrapper package. This package requires installed MSU VQMT Pro or Premium
Home-page: https://github.com/msu-video-group/vqmt_python
Author: Video Compression Team & MSU G&M Lab.
Author-email: video-measure@compression.ru
License: UNKNOWN
Keywords: video,images,compression,codecs,quality,analysis
Platform: UNKNOWN
Requires-Python: >=3.5
